django_nameko_standalone/__init__.py
django_nameko_standalone-2.0.1.dist-info/METADATA
django_nameko_standalone-2.0.1.dist-info/WHEEL
django_nameko_standalone-2.0.1.dist-info/top_level.txt
django_nameko_standalone-2.0.1.dist-info/RECORD
