Metadata-Version: 2.1
Name: django-nameko-standalone
Version: 2.0.1
Summary: Use django into a nameko service
Home-page: https://github.com/jesusenlanet/django-nameko-standalone
Author: Jesus Gutierrez Almazan
Author-email: jesus.pedro.gutierrez.almazan@gmail.com
License: UNKNOWN
Platform: Linux
Classifier: Environment :: Web Environment
Classifier: Intended Audience :: Developers
Classifier: Programming Language :: Python :: 3.6
Classifier: License :: OSI Approved :: MIT License
Classifier: Operating System :: OS Independent
Classifier: Development Status :: 5 - Production/Stable
Classifier: Framework :: Django :: 3.0
Classifier: Topic :: Software Development :: Libraries
Requires-Dist: Django (==3.0.7)
Requires-Dist: nameko (==2.12.0)
